Metadata-Version: 2.1
Name: binary-fractions
Version: 1.0.3
Summary: A Python package for floating-point binary fractions. Do math in base 2!
Home-page: https://github.com/Jonny-exe/binary-fractions
Author: Jonny-exe
Author-email: 
License: GPL3+
Keywords: binary fractions python python3 floating-point high-precision base-2 floating-point-arithmetic binary-fractions twos-complement
Platform: UNKNOWN
